naf_chatgpt_cli/__init__.py
naf_chatgpt_cli/main.py
naf_chatgpt_cli/save_load_history.py
naf_chatgpt_cli-0.2.1.dist-info/METADATA
naf_chatgpt_cli-0.2.1.dist-info/WHEEL
naf_chatgpt_cli-0.2.1.dist-info/entry_points.txt
naf_chatgpt_cli-0.2.1.dist-info/licenses/LICENSE
naf_chatgpt_cli-0.2.1.dist-info/RECORD
