Metadata-Version: 2.4
Name: naf_chatgpt_cli
Version: 0.2.1
Summary: This is a CLI chatGPT for Linux with so beautiful highlighting gpt-5 
License-File: LICENSE
Author: ilin
Author-email: fizruk.ilin@gmail.com
Requires-Python: >=3.9
Classifier: Programming Language :: Python :: 3
Classifier: Programming Language :: Python :: 3.9
Classifier: Programming Language :: Python :: 3.10
Classifier: Programming Language :: Python :: 3.11
Classifier: Programming Language :: Python :: 3.12
Classifier: Programming Language :: Python :: 3.13
Classifier: Programming Language :: Python :: 3.14
Requires-Dist: anyio (==4.9.0)
Requires-Dist: certifi (==2025.4.26)
Requires-Dist: distro (==1.9.0)
Requires-Dist: h11 (==0.16.0)
Requires-Dist: httpcore (==1.0.9)
Requires-Dist: httpx (==0.28.1)
Requires-Dist: idna (==3.10)
Requires-Dist: jiter (==0.9.0)
Requires-Dist: markdown-it-py (==3.0.0)
Requires-Dist: mdurl (==0.1.2)
Requires-Dist: openai (==1.76.2)
Requires-Dist: prompt-toolkit (>=3.0.52,<4.0.0)
Requires-Dist: pydantic (==2.11.4)
Requires-Dist: pydantic-core (==2.33.2)
Requires-Dist: pygments (==2.19.1)
Requires-Dist: rich (==14.0.0)
Requires-Dist: sniffio (==1.3.1)
Requires-Dist: tqdm (==4.67.1)
Requires-Dist: typing-extensions (==4.13.2)
Requires-Dist: typing-inspection (==0.4.0)
